CellGen/__init__.py
CellGen/model.py
CellGen-0.2.1.dist-info/LICENSE
CellGen-0.2.1.dist-info/METADATA
CellGen-0.2.1.dist-info/WHEEL
CellGen-0.2.1.dist-info/top_level.txt
CellGen-0.2.1.dist-info/RECORD
