Metadata-Version: 2.1
Name: CellGen
Version: 0.2.1
Summary: CellGen: a computational model for predicting the cellular response to diverse perturbation
Home-page: https://github.com/JinmiaoChenLab/CellGenpy
Author: Rom Uddamvathanak
Author-email: vathanakuddam@gmai.com
Classifier: Programming Language :: Python :: 3
Classifier: License :: OSI Approved :: MIT License
Classifier: Operating System :: OS Independent
Requires-Python: >=3.10
License-File: LICENSE
Requires-Dist: numpy ==1.24.3
Requires-Dist: pandas ==1.5.3
Requires-Dist: scanpy ==1.10.2
Requires-Dist: scipy ==1.12.0
Requires-Dist: numba ==0.57.1
Requires-Dist: colorcet ==3.0.1
Requires-Dist: scikit-learn ==1.3.2
Requires-Dist: gseapy ==1.1.0
Requires-Dist: seaborn ==0.13.0
Requires-Dist: jupyter
